piccolo_cursor_pagination/__init__.py
piccolo_cursor_pagination/pagination.py
piccolo_cursor_pagination/py.typed
piccolo_cursor_pagination-0.3.0.dist-info/LICENSE
piccolo_cursor_pagination-0.3.0.dist-info/METADATA
piccolo_cursor_pagination-0.3.0.dist-info/WHEEL
piccolo_cursor_pagination-0.3.0.dist-info/top_level.txt
piccolo_cursor_pagination-0.3.0.dist-info/RECORD
