Metadata-Version: 2.1
Name: piccolo-cursor-pagination
Version: 0.3.0
Summary: Cursor pagination for Piccolo ORM
Home-page: https://github.com/piccolo-orm/piccolo_cursor_pagination
Author: sinisaos
Author-email: sinisaos@gmail.com
License: MIT
Platform: UNKNOWN
Classifier: License :: OSI Approved :: MIT License
Classifier: Programming Language :: Python
Classifier: Programming Language :: Python :: 3
Classifier: Programming Language :: Python :: 3.7
Classifier: Programming Language :: Python :: 3.8
Classifier: Programming Language :: Python :: 3.9
Classifier: Programming Language :: Python :: 3.10
Classifier: Programming Language :: Python :: Implementation :: CPython
Requires-Python: >=3.7
License-File: LICENSE
Requires-Dist: fastapi
Requires-Dist: piccolo
